{
  "income": [
    {
      "id": 0,
      "description": "paycheck",
      "transactionType": "income",
      "amount": 100,
      "category": "job"
    },
    {
      "id": 1,
      "description": "gift",
      "transactionType": "income",
      "amount": 50,
      "category": "gifts & unlisted"
    }
  ],
  "expenses": [
    {
      "id": 0,
      "description": "gas",
      "transactionType": "expense",
      "amount": 50,
      "category": "Bills and Utilities"
    },
    {
      "id": 1,
      "description": "cigar",
      "transactionType": "expense",
      "amount": 10,
      "category": "doodad & unlisted"
    }
  ]
}
